src/__init__.py
src/main.py
ppm_cli-0.0.2.dist-info/entry_points.txt
ppm_cli-0.0.2.dist-info/WHEEL
ppm_cli-0.0.2.dist-info/METADATA
ppm_cli-0.0.2.dist-info/RECORD
