Metadata-Version: 2.1
Name: ppm-cli
Version: 0.0.2
Summary: 
Author: markus
Author-email: datamastery87@gmail.com
Requires-Python: >=3.8,<4.0
Classifier: Programming Language :: Python :: 3
Classifier: Programming Language :: Python :: 3.8
Classifier: Programming Language :: Python :: 3.9
Classifier: Programming Language :: Python :: 3.10
Classifier: Programming Language :: Python :: 3.11
Requires-Dist: cookiecutter (>=2.1.1,<3.0.0)
Requires-Dist: typer[all] (>=0.6.0,<0.7.0)
